shoosh/__init__.py
shoosh/_docker.py
shoosh/_log.py
shoosh/_sh.py
shoosh/_version.py
shoosh-1.2rc1.dist-info/METADATA
shoosh-1.2rc1.dist-info/WHEEL
shoosh-1.2rc1.dist-info/top_level.txt
shoosh-1.2rc1.dist-info/RECORD
