Metadata-Version: 2.1
Name: shoosh
Version: 1.2rc1
Summary: Python/sh wrapper for executing commands inside docker containers and mapping host:container volumes
Home-page: https://github.com/chbrandt/shoosh
Author: Carlos H. Brandt
License: UNKNOWN
Keywords: sh,docker
Platform: UNKNOWN
Classifier: Programming Language :: Python :: 3
Classifier: License :: OSI Approved :: MIT License
Classifier: Operating System :: OS Independent
Requires-Python: >=3.6
Requires-Dist: sh (>=1.14)
